{
  "date": "2026-01-17",
  "is_live": false,
  "matchups": [
    {
      "home_team": "DominAYTON",
      "away_team": "Sarr Fox 64",
      "home_avg": 315.0337,
      "away_avg": 478.8126,
      "home_win_prob": 0.0092,
      "away_win_prob": 0.9906,
      "tie_prob": 0.0002,
      "trials": 10000,
      "home_team_url": "https://mystique-api.fantasy.espn.com/apis/v1/domains/lm/images/537cc390-d618-11f0-b1c3-bf61c28fbeb9",
      "away_team_url": "https://i.imgur.com/NIrlLQz.png",
      "home_current_score": 316.0,
      "away_current_score": 149.0
    },
    {
      "home_team": "LeBron's Lemmings",
      "away_team": "Luka's Ozempic Dealer",
      "home_avg": 258.7992,
      "away_avg": 346.0435,
      "home_win_prob": 0.0723,
      "away_win_prob": 0.9253,
      "tie_prob": 0.0024,
      "trials": 10000,
      "home_team_url": "https://g.espncdn.com/lm-static/logo-packs/core/CatsAndDogs/cats_dogs-8.svg",
      "away_team_url": "https://mystique-api.fantasy.espn.com/apis/v1/domains/lm/images/ee16f470-af58-11f0-b1c3-bf61c28fbeb9",
      "home_current_score": 155.0,
      "away_current_score": 189.0
    },
    {
      "home_team": "Freaky Friday",
      "away_team": "Sharpe Shooters",
      "home_avg": 154.1546,
      "away_avg": 324.1759,
      "home_win_prob": 0.0001,
      "away_win_prob": 0.9998,
      "tie_prob": 0.0001,
      "trials": 10000,
      "home_team_url": "https://g.espncdn.com/lm-static/logo-packs/core/StarsAndFlames/stars_flames-7.svg",
      "away_team_url": "https://g.espncdn.com/lm-static/logo-packs/core/Mascots/mascots-4.svg",
      "home_current_score": 67.0,
      "away_current_score": 249.0
    },
    {
      "home_team": "Zion's Nutritionist",
      "away_team": "Team Burnett",
      "home_avg": 209.479,
      "away_avg": 162.5545,
      "home_win_prob": 0.8295,
      "away_win_prob": 0.1652,
      "tie_prob": 0.0053,
      "trials": 10000,
      "home_team_url": "https://mystique-api.fantasy.espn.com/apis/v1/domains/lm/images/248a6d10-ad61-11f0-90f7-112fa0f42e74",
      "away_team_url": "https://g.espncdn.com/lm-static/logo-packs/core/TeamMascots-RobbHarskamp/Team_Mascots-05.svg",
      "home_current_score": 170.0,
      "away_current_score": 331.0
    }
  ],
  "proj_scores": {
    "DominAYTON": 315.0337,
    "Sarr Fox 64": 478.8126,
    "LeBron's Lemmings": 258.7992,
    "Luka's Ozempic Dealer": 346.0435,
    "Freaky Friday": 154.1546,
    "Sharpe Shooters": 324.1759,
    "Zion's Nutritionist": 209.479,
    "Team Burnett": 162.5545
  },
  "current_scores": {
    "DominAYTON": 316.0,
    "Sarr Fox 64": 149.0,
    "LeBron's Lemmings": 155.0,
    "Luka's Ozempic Dealer": 189.0,
    "Freaky Friday": 67.0,
    "Sharpe Shooters": 249.0,
    "Zion's Nutritionist": 170.0,
    "Team Burnett": 331.0
  },
  "win_probs": {
    "DominAYTON": 0.0092,
    "Sarr Fox 64": 0.9906,
    "LeBron's Lemmings": 0.0723,
    "Luka's Ozempic Dealer": 0.9253,
    "Freaky Friday": 0.0001,
    "Sharpe Shooters": 0.9998,
    "Zion's Nutritionist": 0.8295,
    "Team Burnett": 0.1652
  }
}